xtree/__init__.py
xtree/__main__.py
xtree/cli.py
xtree/xtree.py
fadi_xtree-0.2.0.dist-info/LICENSE
fadi_xtree-0.2.0.dist-info/METADATA
fadi_xtree-0.2.0.dist-info/WHEEL
fadi_xtree-0.2.0.dist-info/entry_points.txt
fadi_xtree-0.2.0.dist-info/top_level.txt
fadi_xtree-0.2.0.dist-info/RECORD
