Metadata-Version: 2.1
Name: fadi-xtree
Version: 0.2.0
Summary: Directory tree generator
Author: 1fadi
License: MIT License
Keywords: tree,diagram,terminal
Requires-Python: >=3.7
License-File: LICENSE
